l_pdf_extractor/__init__.py
l_pdf_extractor/extractor.py
l_pdf_extractor-0.2.2.dist-info/METADATA
l_pdf_extractor-0.2.2.dist-info/WHEEL
l_pdf_extractor-0.2.2.dist-info/top_level.txt
l_pdf_extractor-0.2.2.dist-info/RECORD
