Metadata-Version: 2.4
Name: l-pdf-extractor
Version: 0.2.2
Summary: extractor pdf to markdown and PIL image
Author-email: LobyLiang <lobyliang@qq.com>
License: LICENSE
Requires-Python: >=3.11.9
Requires-Dist: opencv-python>=4.12.0.88
Requires-Dist: pip>=25.3
Requires-Dist: pymupdf>=1.26.7
Requires-Dist: paddleocr[all]==3.3.2
Requires-Dist: paddlex==3.3.12
